distfit/__init__.py
distfit/distfit.py
distfit/examples.py
distfit-1.8.9.dist-info/licenses/LICENSE
distfit-1.8.9.dist-info/METADATA
distfit-1.8.9.dist-info/WHEEL
distfit-1.8.9.dist-info/top_level.txt
distfit-1.8.9.dist-info/RECORD
