Metadata-Version: 2.4
Name: distfit
Version: 1.8.9
Summary: distfit is a Python library for probability density fitting.
Author-email: Erdogan Taskesen <erdogant@gmail.com>
License-Expression: MIT
Project-URL: Homepage, https://erdogant.github.io/distfit
Project-URL: Download, https://github.com/erdogant/distfit/archive/{version}.tar.gz
Keywords: distribution-fitting,pdf,cdf,sse,probability density,hypothesis testing,qqplot,density functions,fitting-curve,probability statistics
Classifier: Programming Language :: Python :: 3
Classifier: Operating System :: OS Independent
Classifier: Intended Audience :: Education
Classifier: Intended Audience :: Science/Research
Classifier: Operating System :: Unix
Classifier: Operating System :: Microsoft :: Windows
Classifier: Operating System :: MacOS
Requires-Python: >=3
License-File: LICENSE
Requires-Dist: packaging
Requires-Dist: matplotlib>=3.5.2
Requires-Dist: numpy
Requires-Dist: pandas
Requires-Dist: statsmodels
Requires-Dist: scipy
Requires-Dist: pypickle>=1.1.4
Requires-Dist: colourmap>=1.1.10
Requires-Dist: joblib
Dynamic: license-file
